adders/add1bit.v
module add1bit (input  a, b, c_in,
                output sum, c_out);

   assign sum = a ^ b ^ c_in;
   assign c_out = ((a ^ b) & c_in) | (a & b);
endmodule // add1bit

adders/add2bit.v
`include "add1bit.v"

module add2bit (input [1:0] a, b,
                input c_in,
                output [1:0] sum,
                output c_out);

   // use intermediate carry wire between adders.
   wire c_b;
   add1bit fa1_0(a[0], b[0], 1'b0, sum[0], c_b);
   add1bit fa1_1(a[1], b[1], c_b, sum[1], c_out);
endmodule // add2bit

adders/add4bit.v
`include "add2bit.v"

module add4bit (input [3:0] a, b,
                input c_in,
                output [3:0] sum,
                output c_out);

   // use intermediate carry wire between adders.
   wire c_b;
   add2bit fa2_0(a[0+:2], b[0+:2], 1'b0, sum[0+:2], c_b);
   add2bit fa2_1(a[2+:2], b[2+:2], c_b, sum[2+:2], c_out);
endmodule // add4bit

adders/tb_add4bit.v
// testbench for `add4bit' module.

`timescale 1ns/1ns
`include "add4bit.v"

module tb_add1bit;
   reg [3:0] a, b;
   reg       c_in;

   wire [3:0] sum;
   wire       c_out;

   integer    i;

   add4bit test_add4bit(a, b, c_in, sum, c_out);

   initial begin
      $dumpfile("tb_add4bit.vcd");
      $dumpvars(0, tb_add1bit);

      c_in = 1'b0;
      for (i = 0; i < 256; i = i + 1) begin
         {a, b} = i; #10;
      end;


      $display("success.");
   end // initial begin
endmodule // tb_add4bit

adders/tb_add4bit.vcd
$date
	Sun Sep 12 15:28:31 2021
$end
$version
	Icarus Verilog
$end
$timescale
	1ns
$end
$scope module tb_add1bit $end
$var wire 4 ! sum [3:0] $end
$var wire 1 " c_out $end
$var reg 4 # a [3:0] $end
$var reg 4 $ b [3:0] $end
$var reg 1 % c_in $end
$var integer 32 & i [31:0] $end
$scope module test_add4bit $end
$var wire 4 ' a [3:0] $end
$var wire 4 ( b [3:0] $end
$var wire 1 % c_in $end
$var wire 4 ) sum [3:0] $end
$var wire 1 " c_out $end
$var wire 1 * c_b $end
$scope module fa2_0 $end
$var wire 2 + a [1:0] $end
$var wire 2 , b [1:0] $end
$var wire 1 - c_in $end
$var wire 2 . sum [1:0] $end
$var wire 1 * c_out $end
$var wire 1 / c_b $end
$scope module fa1_0 $end
$var wire 1 0 a $end
$var wire 1 1 b $end
$var wire 1 2 c_in $end
$var wire 1 / c_out $end
$var wire 1 3 sum $end
$upscope $end
$scope module fa1_1 $end
$var wire 1 4 a $end
$var wire 1 5 b $end
$var wire 1 / c_in $end
$var wire 1 * c_out $end
$var wire 1 6 sum $end
$upscope $end
$upscope $end
$scope module fa2_1 $end
$var wire 2 7 a [1:0] $end
$var wire 2 8 b [1:0] $end
$var wire 1 * c_in $end
$var wire 2 9 sum [1:0] $end
$var wire 1 " c_out $end
$var wire 1 : c_b $end
$scope module fa1_0 $end
$var wire 1 ; a $end
$var wire 1 < b $end
$var wire 1 = c_in $end
$var wire 1 : c_out $end
$var wire 1 > sum $end
$upscope $end
$scope module fa1_1 $end
$var wire 1 ? a $end
$var wire 1 @ b $end
$var wire 1 : c_in $end
$var wire 1 " c_out $end
$var wire 1 A sum $end
$upscope $end
$upscope $end
$upscope $end
$upscope $end
$enddefinitions $end
#0
$dumpvars
0A
0@
0?
0>
0=
0<
0;
0:
b0 9
b0 8
b0 7
06
05
04
03
02
01
00
0/
b0 .
0-
b0 ,
b0 +
0*
b0 )
b0 (
b0 '
b0 &
0%
b0 $
b0 #
0"
b0 !
$end
#10
b1 !
b1 )
b1 .
13
11
b1 ,
b1 $
b1 (
b1 &
#20
03
b10 !
b10 )
b10 .
16
01
15
b10 ,
b10 $
b10 (
b10 &
#30
b11 !
b11 )
b11 .
13
11
b11 ,
b11 $
b11 (
b11 &
#40
03
b0 .
06
b100 !
b100 )
b1 9
1>
01
05
1<
b0 ,
b1 8
b100 $
b100 (
b100 &
#50
b101 !
b101 )
b1 .
13
11
b1 ,
b101 $
b101 (
b101 &
#60
03
b110 !
b110 )
b10 .
16
01
15
b10 ,
b110 $
b110 (
b110 &
#70
b111 !
b111 )
b11 .
13
11
b11 ,
b111 $
b111 (
b111 &
#80
03
b0 .
06
0>
b1000 !
b1000 )
b10 9
1A
01
05
0<
1@
b0 ,
b10 8
b1000 $
b1000 (
b1000 &
#90
b1001 !
b1001 )
b1 .
13
11
b1 ,
b1001 $
b1001 (
b1001 &
#100
03
b1010 !
b1010 )
b10 .
16
01
15
b10 ,
b1010 $
b1010 (
b1010 &
#110
b1011 !
b1011 )
b11 .
13
11
b11 ,
b1011 $
b1011 (
b1011 &
#120
03
b0 .
06
b1100 !
b1100 )
b11 9
1>
01
05
1<
b0 ,
b11 8
b1100 $
b1100 (
b1100 &
#130
b1101 !
b1101 )
b1 .
13
11
b1 ,
b1101 $
b1101 (
b1101 &
#140
03
b1110 !
b1110 )
b10 .
16
01
15
b10 ,
b1110 $
b1110 (
b1110 &
#150
b1111 !
b1111 )
b11 .
13
11
b11 ,
b1111 $
b1111 (
b1111 &
#160
b1 .
06
0>
b1 !
b1 )
b0 9
0A
10
01
05
0<
0@
b1 +
b0 ,
b0 8
b1 #
b1 '
b0 $
b0 (
b10000 &
#170
16
b10 !
b10 )
b10 .
03
1/
11
b1 ,
b1 $
b1 (
b10001 &
#180
0*
13
0/
b11 !
b11 )
b11 .
16
01
15
b10 ,
b10 $
b10 (
b10010 &
#190
1*
06
b0 !
b0 )
b0 .
03
1/
11
b11 ,
b11 $
b11 (
b10011 &
#200
0*
13
0/
b1 .
06
b101 !
b101 )
b1 9
1>
01
05
1<
b0 ,
b1 8
b100 $
b100 (
b10100 &
#210
16
b110 !
b110 )
b10 .
03
1/
11
b1 ,
b101 $
b101 (
b10101 &
#220
0*
13
0/
b111 !
b111 )
b11 .
16
01
15
b10 ,
b110 $
b110 (
b10110 &
#230
1*
06
b100 !
b100 )
b0 .
03
1/
11
b11 ,
b111 $
b111 (
b10111 &
#240
0*
13
0/
b1 .
06
0>
b1001 !
b1001 )
b10 9
1A
01
05
0<
1@
b0 ,
b10 8
b1000 $
b1000 (
b11000 &
#250
16
b1010 !
b1010 )
b10 .
03
1/
11
b1 ,
b1001 $
b1001 (
b11001 &
#260
0*
13
0/
b1011 !
b1011 )
b11 .
16
01
15
b10 ,
b1010 $
b1010 (
b11010 &
#270
1*
06
b1000 !
b1000 )
b0 .
03
1/
11
b11 ,
b1011 $
b1011 (
b11011 &
#280
0*
13
0/
b1 .
06
b1101 !
b1101 )
b11 9
1>
01
05
1<
b0 ,
b11 8
b1100 $
b1100 (
b11100 &
#290
16
b1110 !
b1110 )
b10 .
03
1/
11
b1 ,
b1101 $
b1101 (
b11101 &
#300
0*
13
0/
b1111 !
b1111 )
b11 .
16
01
15
b10 ,
b1110 $
b1110 (
b11110 &
#310
1*
06
b1100 !
b1100 )
b0 .
03
1/
11
b11 ,
b1111 $
b1111 (
b11111 &
#320
0*
b10 .
16
0/
0>
b10 !
b10 )
b0 9
0A
00
14
01
05
0<
0@
b10 +
b0 ,
b0 8
b10 #
b10 '
b0 $
b0 (
b100000 &
#330
b11 !
b11 )
b11 .
13
11
b1 ,
b1 $
b1 (
b100001 &
#340
03
b0 !
b0 )
b0 .
06
1*
01
15
b10 ,
b10 $
b10 (
b100010 &
#350
b1 !
b1 )
b1 .
13
11
b11 ,
b11 $
b11 (
b100011 &
#360
03
b10 .
16
0*
b110 !
b110 )
b1 9
1>
01
05
1<
b0 ,
b1 8
b100 $
b100 (
b100100 &
#370
b111 !
b111 )
b11 .
13
11
b1 ,
b101 $
b101 (
b100101 &
#380
03
b100 !
b100 )
b0 .
06
1*
01
15
b10 ,
b110 $
b110 (
b100110 &
#390
b101 !
b101 )
b1 .
13
11
b11 ,
b111 $
b111 (
b100111 &
#400
03
b10 .
16
0*
0>
b1010 !
b1010 )
b10 9
1A
01
05
0<
1@
b0 ,
b10 8
b1000 $
b1000 (
b101000 &
#410
b1011 !
b1011 )
b11 .
13
11
b1 ,
b1001 $
b1001 (
b101001 &
#420
03
b1000 !
b1000 )
b0 .
06
1*
01
15
b10 ,
b1010 $
b1010 (
b101010 &
#430
b1001 !
b1001 )
b1 .
13
11
b11 ,
b1011 $
b1011 (
b101011 &
#440
03
b10 .
16
0*
b1110 !
b1110 )
b11 9
1>
01
05
1<
b0 ,
b11 8
b1100 $
b1100 (
b101100 &
#450
b1111 !
b1111 )
b11 .
13
11
b1 ,
b1101 $
b1101 (
b101101 &
#460
03
b1100 !
b1100 )
b0 .
06
1*
01
15
b10 ,
b1110 $
b1110 (
b101110 &
#470
b1101 !
b1101 )
b1 .
13
11
b11 ,
b1111 $
b1111 (
b101111 &
#480
b11 .
16
0*
0>
b11 !
b11 )
b0 9
0A
10
01
05
0<
0@
b11 +
b0 ,
b0 8
b11 #
b11 '
b0 $
b0 (
b110000 &
#490
1*
06
b0 !
b0 )
b0 .
03
1/
11
b1 ,
b1 $
b1 (
b110001 &
#500
13
0/
b1 !
b1 )
b1 .
06
01
15
b10 ,
b10 $
b10 (
b110010 &
#510
16
b10 !
b10 )
b10 .
03
1/
11
b11 ,
b11 $
b11 (
b110011 &
#520
13
0/
b11 .
16
0*
b111 !
b111 )
b1 9
1>
01
05
1<
b0 ,
b1 8
b100 $
b100 (
b110100 &
#530
1*
06
b100 !
b100 )
b0 .
03
1/
11
b1 ,
b101 $
b101 (
b110101 &
#540
13
0/
b101 !
b101 )
b1 .
06
01
15
b10 ,
b110 $
b110 (
b110110 &
#550
16
b110 !
b110 )
b10 .
03
1/
11
b11 ,
b111 $
b111 (
b110111 &
#560
13
0/
b11 .
16
0*
0>
b1011 !
b1011 )
b10 9
1A
01
05
0<
1@
b0 ,
b10 8
b1000 $
b1000 (
b111000 &
#570
1*
06
b1000 !
b1000 )
b0 .
03
1/
11
b1 ,
b1001 $
b1001 (
b111001 &
#580
13
0/
b1001 !
b1001 )
b1 .
06
01
15
b10 ,
b1010 $
b1010 (
b111010 &
#590
16
b1010 !
b1010 )
b10 .
03
1/
11
b11 ,
b1011 $
b1011 (
b111011 &
#600
13
0/
b11 .
16
0*
b1111 !
b1111 )
b11 9
1>
01
05
1<
b0 ,
b11 8
b1100 $
b1100 (
b111100 &
#610
1*
06
b1100 !
b1100 )
b0 .
03
1/
11
b1 ,
b1101 $
b1101 (
b111101 &
#620
13
0/
b1101 !
b1101 )
b1 .
06
01
15
b10 ,
b1110 $
b1110 (
b111110 &
#630
16
b1110 !
b1110 )
b10 .
03
1/
11
b11 ,
b1111 $
b1111 (
b111111 &
#640
b0 .
06
0/
0*
b100 !
b100 )
b1 9
0A
00
04
1;
01
05
0<
0@
b0 +
b1 7
b0 ,
b0 8
b100 #
b100 '
b0 $
b0 (
b1000000 &
#650
b101 !
b101 )
b1 .
13
11
b1 ,
b1 $
b1 (
b1000001 &
#660
03
b110 !
b110 )
b10 .
16
01
15
b10 ,
b10 $
b10 (
b1000010 &
#670
b111 !
b111 )
b11 .
13
11
b11 ,
b11 $
b11 (
b1000011 &
#680
1A
03
b0 .
06
b1000 !
b1000 )
b10 9
0>
1:
01
05
1<
b0 ,
b1 8
b100 $
b100 (
b1000100 &
#690
b1001 !
b1001 )
b1 .
13
11
b1 ,
b101 $
b101 (
b1000101 &
#700
03
b1010 !
b1010 )
b10 .
16
01
15
b10 ,
b110 $
b110 (
b1000110 &
#710
b1011 !
b1011 )
b11 .
13
11
b11 ,
b111 $
b111 (
b1000111 &
#720
0"
03
b0 .
06
1>
0:
b1100 !
b1100 )
b11 9
1A
01
05
0<
1@
b0 ,
b10 8
b1000 $
b1000 (
b1001000 &
#730
b1101 !
b1101 )
b1 .
13
11
b1 ,
b1001 $
b1001 (
b1001001 &
#740
03
b1110 !
b1110 )
b10 .
16
01
15
b10 ,
b1010 $
b1010 (
b1001010 &
#750
b1111 !
b1111 )
b11 .
13
11
b11 ,
b1011 $
b1011 (
b1001011 &
#760
1"
0A
03
b0 .
06
b0 !
b0 )
b0 9
0>
1:
01
05
1<
b0 ,
b11 8
b1100 $
b1100 (
b1001100 &
#770
b1 !
b1 )
b1 .
13
11
b1 ,
b1101 $
b1101 (
b1001101 &
#780
03
b10 !
b10 )
b10 .
16
01
15
b10 ,
b1110 $
b1110 (
b1001110 &
#790
b11 !
b11 )
b11 .
13
11
b11 ,
b1111 $
b1111 (
b1001111 &
#800
0"
b1 .
06
1>
0:
b101 !
b101 )
b1 9
0A
10
01
05
0<
0@
b1 +
b0 ,
b0 8
b101 #
b101 '
b0 $
b0 (
b1010000 &
#810
16
b110 !
b110 )
b10 .
03
1/
11
b1 ,
b1 $
b1 (
b1010001 &
#820
0*
13
0/
b111 !
b111 )
b11 .
16
01
15
b10 ,
b10 $
b10 (
b1010010 &
#830
1*
06
b100 !
b100 )
b0 .
03
1/
11
b11 ,
b11 $
b11 (
b1010011 &
#840
0*
1A
13
0/
b1 .
06
b1001 !
b1001 )
b10 9
0>
1:
01
05
1<
b0 ,
b1 8
b100 $
b100 (
b1010100 &
#850
16
b1010 !
b1010 )
b10 .
03
1/
11
b1 ,
b101 $
b101 (
b1010101 &
#860
0*
13
0/
b1011 !
b1011 )
b11 .
16
01
15
b10 ,
b110 $
b110 (
b1010110 &
#870
1*
06
b1000 !
b1000 )
b0 .
03
1/
11
b11 ,
b111 $
b111 (
b1010111 &
#880
0*
0"
13
0/
b1 .
06
1>
0:
b1101 !
b1101 )
b11 9
1A
01
05
0<
1@
b0 ,
b10 8
b1000 $
b1000 (
b1011000 &
#890
16
b1110 !
b1110 )
b10 .
03
1/
11
b1 ,
b1001 $
b1001 (
b1011001 &
#900
0*
13
0/
b1111 !
b1111 )
b11 .
16
01
15
b10 ,
b1010 $
b1010 (
b1011010 &
#910
1*
06
b1100 !
b1100 )
b0 .
03
1/
11
b11 ,
b1011 $
b1011 (
b1011011 &
#920
1"
0*
0A
13
0/
b1 .
06
b1 !
b1 )
b0 9
0>
1:
01
05
1<
b0 ,
b11 8
b1100 $
b1100 (
b1011100 &
#930
16
b10 !
b10 )
b10 .
03
1/
11
b1 ,
b1101 $
b1101 (
b1011101 &
#940
0*
13
0/
b11 !
b11 )
b11 .
16
01
15
b10 ,
b1110 $
b1110 (
b1011110 &
#950
1*
06
b0 !
b0 )
b0 .
03
1/
11
b11 ,
b1111 $
b1111 (
b1011111 &
#960
0*
b10 .
16
0"
0/
1>
0:
b110 !
b110 )
b1 9
0A
00
14
01
05
0<
0@
b10 +
b0 ,
b0 8
b110 #
b110 '
b0 $
b0 (
b1100000 &
#970
b111 !
b111 )
b11 .
13
11
b1 ,
b1 $
b1 (
b1100001 &
#980
03
b100 !
b100 )
b0 .
06
1*
01
15
b10 ,
b10 $
b10 (
b1100010 &
#990
b101 !
b101 )
b1 .
13
11
b11 ,
b11 $
b11 (
b1100011 &
#1000
1A
03
b10 .
16
0*
b1010 !
b1010 )
b10 9
0>
1:
01
05
1<
b0 ,
b1 8
b100 $
b100 (
b1100100 &
#1010
b1011 !
b1011 )
b11 .
13
11
b1 ,
b101 $
b101 (
b1100101 &
#1020
03
b1000 !
b1000 )
b0 .
06
1*
01
15
b10 ,
b110 $
b110 (
b1100110 &
#1030
b1001 !
b1001 )
b1 .
13
11
b11 ,
b111 $
b111 (
b1100111 &
#1040
0"
03
b10 .
16
0*
1>
0:
b1110 !
b1110 )
b11 9
1A
01
05
0<
1@
b0 ,
b10 8
b1000 $
b1000 (
b1101000 &
#1050
b1111 !
b1111 )
b11 .
13
11
b1 ,
b1001 $
b1001 (
b1101001 &
#1060
03
b1100 !
b1100 )
b0 .
06
1*
01
15
b10 ,
b1010 $
b1010 (
b1101010 &
#1070
b1101 !
b1101 )
b1 .
13
11
b11 ,
b1011 $
b1011 (
b1101011 &
#1080
1"
0A
03
b10 .
16
0*
b10 !
b10 )
b0 9
0>
1:
01
05
1<
b0 ,
b11 8
b1100 $
b1100 (
b1101100 &
#1090
b11 !
b11 )
b11 .
13
11
b1 ,
b1101 $
b1101 (
b1101101 &
#1100
03
b0 !
b0 )
b0 .
06
1*
01
15
b10 ,
b1110 $
b1110 (
b1101110 &
#1110
b1 !
b1 )
b1 .
13
11
b11 ,
b1111 $
b1111 (
b1101111 &
#1120
0"
b11 .
16
0*
1>
0:
b111 !
b111 )
b1 9
0A
10
01
05
0<
0@
b11 +
b0 ,
b0 8
b111 #
b111 '
b0 $
b0 (
b1110000 &
#1130
1*
06
b100 !
b100 )
b0 .
03
1/
11
b1 ,
b1 $
b1 (
b1110001 &
#1140
13
0/
b101 !
b101 )
b1 .
06
01
15
b10 ,
b10 $
b10 (
b1110010 &
#1150
16
b110 !
b110 )
b10 .
03
1/
11
b11 ,
b11 $
b11 (
b1110011 &
#1160
1A
13
0/
b11 .
16
0*
b1011 !
b1011 )
b10 9
0>
1:
01
05
1<
b0 ,
b1 8
b100 $
b100 (
b1110100 &
#1170
1*
06
b1000 !
b1000 )
b0 .
03
1/
11
b1 ,
b101 $
b101 (
b1110101 &
#1180
13
0/
b1001 !
b1001 )
b1 .
06
01
15
b10 ,
b110 $
b110 (
b1110110 &
#1190
16
b1010 !
b1010 )
b10 .
03
1/
11
b11 ,
b111 $
b111 (
b1110111 &
#1200
0"
13
0/
b11 .
16
0*
1>
0:
b1111 !
b1111 )
b11 9
1A
01
05
0<
1@
b0 ,
b10 8
b1000 $
b1000 (
b1111000 &
#1210
1*
06
b1100 !
b1100 )
b0 .
03
1/
11
b1 ,
b1001 $
b1001 (
b1111001 &
#1220
13
0/
b1101 !
b1101 )
b1 .
06
01
15
b10 ,
b1010 $
b1010 (
b1111010 &
#1230
16
b1110 !
b1110 )
b10 .
03
1/
11
b11 ,
b1011 $
b1011 (
b1111011 &
#1240
1"
0A
13
0/
b11 .
16
0*
b11 !
b11 )
b0 9
0>
1:
01
05
1<
b0 ,
b11 8
b1100 $
b1100 (
b1111100 &
#1250
1*
06
b0 !
b0 )
b0 .
03
1/
11
b1 ,
b1101 $
b1101 (
b1111101 &
#1260
13
0/
b1 !
b1 )
b1 .
06
01
15
b10 ,
b1110 $
b1110 (
b1111110 &
#1270
16
b10 !
b10 )
b10 .
03
1/
11
b11 ,
b1111 $
b1111 (
b1111111 &
#1280
0"
b0 .
06
b1000 !
b1000 )
b10 9
1A
0/
0*
0:
00
04
0;
1?
01
05
0<
0@
b0 +
b10 7
b0 ,
b0 8
b1000 #
b1000 '
b0 $
b0 (
b10000000 &
#1290
b1001 !
b1001 )
b1 .
13
11
b1 ,
b1 $
b1 (
b10000001 &
#1300
03
b1010 !
b1010 )
b10 .
16
01
15
b10 ,
b10 $
b10 (
b10000010 &
#1310
b1011 !
b1011 )
b11 .
13
11
b11 ,
b11 $
b11 (
b10000011 &
#1320
03
b0 .
06
b1100 !
b1100 )
b11 9
1>
01
05
1<
b0 ,
b1 8
b100 $
b100 (
b10000100 &
#1330
b1101 !
b1101 )
b1 .
13
11
b1 ,
b101 $
b101 (
b10000101 &
#1340
03
b1110 !
b1110 )
b10 .
16
01
15
b10 ,
b110 $
b110 (
b10000110 &
#1350
b1111 !
b1111 )
b11 .
13
11
b11 ,
b111 $
b111 (
b10000111 &
#1360
03
b0 .
06
0>
b0 !
b0 )
b0 9
0A
1"
01
05
0<
1@
b0 ,
b10 8
b1000 $
b1000 (
b10001000 &
#1370
b1 !
b1 )
b1 .
13
11
b1 ,
b1001 $
b1001 (
b10001001 &
#1380
03
b10 !
b10 )
b10 .
16
01
15
b10 ,
b1010 $
b1010 (
b10001010 &
#1390
b11 !
b11 )
b11 .
13
11
b11 ,
b1011 $
b1011 (
b10001011 &
#1400
03
b0 .
06
b100 !
b100 )
b1 9
1>
01
05
1<
b0 ,
b11 8
b1100 $
b1100 (
b10001100 &
#1410
b101 !
b101 )
b1 .
13
11
b1 ,
b1101 $
b1101 (
b10001101 &
#1420
03
b110 !
b110 )
b10 .
16
01
15
b10 ,
b1110 $
b1110 (
b10001110 &
#1430
b111 !
b111 )
b11 .
13
11
b11 ,
b1111 $
b1111 (
b10001111 &
#1440
b1 .
06
0>
b1001 !
b1001 )
b10 9
1A
0"
10
01
05
0<
0@
b1 +
b0 ,
b0 8
b1001 #
b1001 '
b0 $
b0 (
b10010000 &
#1450
16
b1010 !
b1010 )
b10 .
03
1/
11
b1 ,
b1 $
b1 (
b10010001 &
#1460
0*
13
0/
b1011 !
b1011 )
b11 .
16
01
15
b10 ,
b10 $
b10 (
b10010010 &
#1470
1*
06
b1000 !
b1000 )
b0 .
03
1/
11
b11 ,
b11 $
b11 (
b10010011 &
#1480
0*
13
0/
b1 .
06
b1101 !
b1101 )
b11 9
1>
01
05
1<
b0 ,
b1 8
b100 $
b100 (
b10010100 &
#1490
16
b1110 !
b1110 )
b10 .
03
1/
11
b1 ,
b101 $
b101 (
b10010101 &
#1500
0*
13
0/
b1111 !
b1111 )
b11 .
16
01
15
b10 ,
b110 $
b110 (
b10010110 &
#1510
1*
06
b1100 !
b1100 )
b0 .
03
1/
11
b11 ,
b111 $
b111 (
b10010111 &
#1520
0*
13
0/
b1 .
06
0>
b1 !
b1 )
b0 9
0A
1"
01
05
0<
1@
b0 ,
b10 8
b1000 $
b1000 (
b10011000 &
#1530
16
b10 !
b10 )
b10 .
03
1/
11
b1 ,
b1001 $
b1001 (
b10011001 &
#1540
0*
13
0/
b11 !
b11 )
b11 .
16
01
15
b10 ,
b1010 $
b1010 (
b10011010 &
#1550
1*
06
b0 !
b0 )
b0 .
03
1/
11
b11 ,
b1011 $
b1011 (
b10011011 &
#1560
0*
13
0/
b1 .
06
b101 !
b101 )
b1 9
1>
01
05
1<
b0 ,
b11 8
b1100 $
b1100 (
b10011100 &
#1570
16
b110 !
b110 )
b10 .
03
1/
11
b1 ,
b1101 $
b1101 (
b10011101 &
#1580
0*
13
0/
b111 !
b111 )
b11 .
16
01
15
b10 ,
b1110 $
b1110 (
b10011110 &
#1590
1*
06
b100 !
b100 )
b0 .
03
1/
11
b11 ,
b1111 $
b1111 (
b10011111 &
#1600
0*
b10 .
16
0/
0>
b1010 !
b1010 )
b10 9
1A
0"
00
14
01
05
0<
0@
b10 +
b0 ,
b0 8
b1010 #
b1010 '
b0 $
b0 (
b10100000 &
#1610
b1011 !
b1011 )
b11 .
13
11
b1 ,
b1 $
b1 (
b10100001 &
#1620
03
b1000 !
b1000 )
b0 .
06
1*
01
15
b10 ,
b10 $
b10 (
b10100010 &
#1630
b1001 !
b1001 )
b1 .
13
11
b11 ,
b11 $
b11 (
b10100011 &
#1640
03
b10 .
16
0*
b1110 !
b1110 )
b11 9
1>
01
05
1<
b0 ,
b1 8
b100 $
b100 (
b10100100 &
#1650
b1111 !
b1111 )
b11 .
13
11
b1 ,
b101 $
b101 (
b10100101 &
#1660
03
b1100 !
b1100 )
b0 .
06
1*
01
15
b10 ,
b110 $
b110 (
b10100110 &
#1670
b1101 !
b1101 )
b1 .
13
11
b11 ,
b111 $
b111 (
b10100111 &
#1680
03
b10 .
16
0*
0>
b10 !
b10 )
b0 9
0A
1"
01
05
0<
1@
b0 ,
b10 8
b1000 $
b1000 (
b10101000 &
#1690
b11 !
b11 )
b11 .
13
11
b1 ,
b1001 $
b1001 (
b10101001 &
#1700
03
b0 !
b0 )
b0 .
06
1*
01
15
b10 ,
b1010 $
b1010 (
b10101010 &
#1710
b1 !
b1 )
b1 .
13
11
b11 ,
b1011 $
b1011 (
b10101011 &
#1720
03
b10 .
16
0*
b110 !
b110 )
b1 9
1>
01
05
1<
b0 ,
b11 8
b1100 $
b1100 (
b10101100 &
#1730
b111 !
b111 )
b11 .
13
11
b1 ,
b1101 $
b1101 (
b10101101 &
#1740
03
b100 !
b100 )
b0 .
06
1*
01
15
b10 ,
b1110 $
b1110 (
b10101110 &
#1750
b101 !
b101 )
b1 .
13
11
b11 ,
b1111 $
b1111 (
b10101111 &
#1760
b11 .
16
0*
0>
b1011 !
b1011 )
b10 9
1A
0"
10
01
05
0<
0@
b11 +
b0 ,
b0 8
b1011 #
b1011 '
b0 $
b0 (
b10110000 &
#1770
1*
06
b1000 !
b1000 )
b0 .
03
1/
11
b1 ,
b1 $
b1 (
b10110001 &
#1780
13
0/
b1001 !
b1001 )
b1 .
06
01
15
b10 ,
b10 $
b10 (
b10110010 &
#1790
16
b1010 !
b1010 )
b10 .
03
1/
11
b11 ,
b11 $
b11 (
b10110011 &
#1800
13
0/
b11 .
16
0*
b1111 !
b1111 )
b11 9
1>
01
05
1<
b0 ,
b1 8
b100 $
b100 (
b10110100 &
#1810
1*
06
b1100 !
b1100 )
b0 .
03
1/
11
b1 ,
b101 $
b101 (
b10110101 &
#1820
13
0/
b1101 !
b1101 )
b1 .
06
01
15
b10 ,
b110 $
b110 (
b10110110 &
#1830
16
b1110 !
b1110 )
b10 .
03
1/
11
b11 ,
b111 $
b111 (
b10110111 &
#1840
13
0/
b11 .
16
0*
0>
b11 !
b11 )
b0 9
0A
1"
01
05
0<
1@
b0 ,
b10 8
b1000 $
b1000 (
b10111000 &
#1850
1*
06
b0 !
b0 )
b0 .
03
1/
11
b1 ,
b1001 $
b1001 (
b10111001 &
#1860
13
0/
b1 !
b1 )
b1 .
06
01
15
b10 ,
b1010 $
b1010 (
b10111010 &
#1870
16
b10 !
b10 )
b10 .
03
1/
11
b11 ,
b1011 $
b1011 (
b10111011 &
#1880
13
0/
b11 .
16
0*
b111 !
b111 )
b1 9
1>
01
05
1<
b0 ,
b11 8
b1100 $
b1100 (
b10111100 &
#1890
1*
06
b100 !
b100 )
b0 .
03
1/
11
b1 ,
b1101 $
b1101 (
b10111101 &
#1900
13
0/
b101 !
b101 )
b1 .
06
01
15
b10 ,
b1110 $
b1110 (
b10111110 &
#1910
16
b110 !
b110 )
b10 .
03
1/
11
b11 ,
b1111 $
b1111 (
b10111111 &
#1920
b0 .
06
0/
0*
b1100 !
b1100 )
b11 9
1A
0"
00
04
1;
01
05
0<
0@
b0 +
b11 7
b0 ,
b0 8
b1100 #
b1100 '
b0 $
b0 (
b11000000 &
#1930
b1101 !
b1101 )
b1 .
13
11
b1 ,
b1 $
b1 (
b11000001 &
#1940
03
b1110 !
b1110 )
b10 .
16
01
15
b10 ,
b10 $
b10 (
b11000010 &
#1950
b1111 !
b1111 )
b11 .
13
11
b11 ,
b11 $
b11 (
b11000011 &
#1960
1"
0A
03
b0 .
06
b0 !
b0 )
b0 9
0>
1:
01
05
1<
b0 ,
b1 8
b100 $
b100 (
b11000100 &
#1970
b1 !
b1 )
b1 .
13
11
b1 ,
b101 $
b101 (
b11000101 &
#1980
03
b10 !
b10 )
b10 .
16
01
15
b10 ,
b110 $
b110 (
b11000110 &
#1990
b11 !
b11 )
b11 .
13
11
b11 ,
b111 $
b111 (
b11000111 &
#2000
03
b0 .
06
1>
0:
b100 !
b100 )
b1 9
0A
01
05
0<
1@
b0 ,
b10 8
b1000 $
b1000 (
b11001000 &
#2010
b101 !
b101 )
b1 .
13
11
b1 ,
b1001 $
b1001 (
b11001001 &
#2020
03
b110 !
b110 )
b10 .
16
01
15
b10 ,
b1010 $
b1010 (
b11001010 &
#2030
b111 !
b111 )
b11 .
13
11
b11 ,
b1011 $
b1011 (
b11001011 &
#2040
1A
03
b0 .
06
b1000 !
b1000 )
b10 9
0>
1:
01
05
1<
b0 ,
b11 8
b1100 $
b1100 (
b11001100 &
#2050
b1001 !
b1001 )
b1 .
13
11
b1 ,
b1101 $
b1101 (
b11001101 &
#2060
03
b1010 !
b1010 )
b10 .
16
01
15
b10 ,
b1110 $
b1110 (
b11001110 &
#2070
b1011 !
b1011 )
b11 .
13
11
b11 ,
b1111 $
b1111 (
b11001111 &
#2080
b1 .
06
1>
0:
b1101 !
b1101 )
b11 9
1A
0"
10
01
05
0<
0@
b1 +
b0 ,
b0 8
b1101 #
b1101 '
b0 $
b0 (
b11010000 &
#2090
16
b1110 !
b1110 )
b10 .
03
1/
11
b1 ,
b1 $
b1 (
b11010001 &
#2100
0*
13
0/
b1111 !
b1111 )
b11 .
16
01
15
b10 ,
b10 $
b10 (
b11010010 &
#2110
1*
06
b1100 !
b1100 )
b0 .
03
1/
11
b11 ,
b11 $
b11 (
b11010011 &
#2120
1"
0*
0A
13
0/
b1 .
06
b1 !
b1 )
b0 9
0>
1:
01
05
1<
b0 ,
b1 8
b100 $
b100 (
b11010100 &
#2130
16
b10 !
b10 )
b10 .
03
1/
11
b1 ,
b101 $
b101 (
b11010101 &
#2140
0*
13
0/
b11 !
b11 )
b11 .
16
01
15
b10 ,
b110 $
b110 (
b11010110 &
#2150
1*
06
b0 !
b0 )
b0 .
03
1/
11
b11 ,
b111 $
b111 (
b11010111 &
#2160
0*
13
0/
b1 .
06
1>
0:
b101 !
b101 )
b1 9
0A
01
05
0<
1@
b0 ,
b10 8
b1000 $
b1000 (
b11011000 &
#2170
16
b110 !
b110 )
b10 .
03
1/
11
b1 ,
b1001 $
b1001 (
b11011001 &
#2180
0*
13
0/
b111 !
b111 )
b11 .
16
01
15
b10 ,
b1010 $
b1010 (
b11011010 &
#2190
1*
06
b100 !
b100 )
b0 .
03
1/
11
b11 ,
b1011 $
b1011 (
b11011011 &
#2200
0*
1A
13
0/
b1 .
06
b1001 !
b1001 )
b10 9
0>
1:
01
05
1<
b0 ,
b11 8
b1100 $
b1100 (
b11011100 &
#2210
16
b1010 !
b1010 )
b10 .
03
1/
11
b1 ,
b1101 $
b1101 (
b11011101 &
#2220
0*
13
0/
b1011 !
b1011 )
b11 .
16
01
15
b10 ,
b1110 $
b1110 (
b11011110 &
#2230
1*
06
b1000 !
b1000 )
b0 .
03
1/
11
b11 ,
b1111 $
b1111 (
b11011111 &
