adders/add1bit.v
module add1bit (input  a, b, c_in,
                output sum, c_out);

   assign sum = a ^ b ^ c_in;
   assign c_out = ((a ^ b) & c_in) | (a & b);
endmodule // add1bit

adders/add2bit.v
`include "add1bit.v"

module add2bit (input [1:0] a, b,
                input c_in,
                output [1:0] sum,
                output c_out);

   // use intermediate carry wire between adders.
   wire c_b;
   add1bit fa1_0(a[0], b[0], 1'b0, sum[0], c_b);
   add1bit fa1_1(a[1], b[1], c_b, sum[1], c_out);
endmodule // add2bit

adders/tb_add2bit.v
// testbench for `add2bit' module.

`timescale 1ns/1ns
`include "add2bit.v"

module tb_add1bit;
   reg [1:0] a, b;
   reg       c_in;

   wire [1:0] sum;
   wire       c_out;

   add2bit test_add2bit(a, b, c_in, sum, c_out);

   initial begin
      $dumpfile("tb_add2bit.vcd");
      $dumpvars(0, tb_add1bit);

      {a, b} = 4'b0000;
      c_in = c_out; #10;
      {a, b} = 4'b0001;
      c_in = c_out; #10;
      {a, b} = 4'b0010;
      c_in = c_out; #10;
      {a, b} = 4'b0011;
      c_in = c_out; #10;
      {a, b} = 4'b0100;
      c_in = c_out; #10;
      {a, b} = 4'b0101;
      c_in = c_out; #10;
      {a, b} = 4'b0110;
      c_in = c_out; #10;
      {a, b} = 4'b0111;
      c_in = c_out; #10;
      {a, b} = 4'b1000;
      c_in = c_out; #10;
      {a, b} = 4'b1001;
      c_in = c_out; #10;
      {a, b} = 4'b1010;
      c_in = c_out; #10;
      {a, b} = 4'b1011;
      c_in = c_out; #10;
      {a, b} = 4'b1111;
      c_in = c_out; #10;

      $display("success.");
   end // initial begin
endmodule // tb_add2bit

adders/tb_add2bit.vcd
$date
	Sun Sep 12 15:28:22 2021
$end
$version
	Icarus Verilog
$end
$timescale
	1ns
$end
$scope module tb_add1bit $end
$var wire 2 ! sum [1:0] $end
$var wire 1 " c_out $end
$var reg 2 # a [1:0] $end
$var reg 2 $ b [1:0] $end
$var reg 1 % c_in $end
$scope module test_add2bit $end
$var wire 2 & a [1:0] $end
$var wire 2 ' b [1:0] $end
$var wire 1 % c_in $end
$var wire 2 ( sum [1:0] $end
$var wire 1 " c_out $end
$var wire 1 ) c_b $end
$scope module fa1_0 $end
$var wire 1 * a $end
$var wire 1 + b $end
$var wire 1 , c_in $end
$var wire 1 ) c_out $end
$var wire 1 - sum $end
$upscope $end
$scope module fa1_1 $end
$var wire 1 . a $end
$var wire 1 / b $end
$var wire 1 ) c_in $end
$var wire 1 " c_out $end
$var wire 1 0 sum $end
$upscope $end
$upscope $end
$upscope $end
$enddefinitions $end
#0
$dumpvars
00
0/
0.
0-
0,
0+
0*
0)
b0 (
b0 '
b0 &
0%
b0 $
b0 #
0"
b0 !
$end
#10
b1 !
b1 (
1-
1+
b1 $
b1 '
#20
0-
b10 !
b10 (
10
0+
1/
b10 $
b10 '
#30
b11 !
b11 (
1-
1+
b11 $
b11 '
#40
b1 !
b1 (
00
1*
0+
0/
b1 #
b1 &
b0 $
b0 '
#50
10
b10 !
b10 (
0-
1)
1+
b1 $
b1 '
#60
0"
1-
0)
b11 !
b11 (
10
0+
1/
b10 $
b10 '
#70
1"
00
b0 !
b0 (
0-
1)
1+
b11 $
b11 '
#80
0"
b10 !
b10 (
10
0)
0*
1.
0+
0/
b10 #
b10 &
b0 $
b0 '
#90
b11 !
b11 (
1-
1+
b1 $
b1 '
#100
0-
b0 !
b0 (
00
1"
0+
1/
b10 $
b10 '
#110
b1 !
b1 (
1-
1+
b11 $
b11 '
#120
10
b10 !
b10 (
0-
1)
1*
b11 #
b11 &
