control-flow/greater.v
// compare two 2-bit numbers and send 1'b1 to `out'
// if the first one is greater than the second one
// and 1'b0 otherwise.

module greater (input [1:0] a, b,
                output      out);

   // can be done like that:
   // assign out = a > b;
   assign out = a[1] & ~b[1] | a[0] & ~b[1] & ~b[0] | a[1] & a[0] & ~b[0];
endmodule // greater

control-flow/tb_greater.v
// testbench for `greater` module.

`timescale 1ns/1ns
`include "greater.v"

module tb_greater;
   reg [1:0] a;
   reg [1:0] b;
   wire      out;

   greater test_greater(a, b, out);

   initial begin
      $dumpfile("tb_greater.vcd");
      $dumpvars(0, tb_greater);

      {a, b} = 4'b0000; #1;
      {a, b} = 4'b0001; #1;
      {a, b} = 4'b0010; #1;
      {a, b} = 4'b0011; #1;
      {a, b} = 4'b0100; #1;
      {a, b} = 4'b0101; #1;
      {a, b} = 4'b0110; #1;
      {a, b} = 4'b0111; #1;
      {a, b} = 4'b1000; #1;
      {a, b} = 4'b1001; #1;
      {a, b} = 4'b1010; #1;
      {a, b} = 4'b1011; #1;
      {a, b} = 4'b1100; #1;
      {a, b} = 4'b1101; #1;
      {a, b} = 4'b1110; #1;
      {a, b} = 4'b1111; #1;

      $display("success");
   end // initial begin
endmodule

control-flow/tb_greater.vcd
$date
	Sun Sep 12 13:35:36 2021
$end
$version
	Icarus Verilog
$end
$timescale
	1ns
$end
$scope module tb_greater $end
$var wire 1 ! out $end
$var reg 2 " a [1:0] $end
$var reg 2 # b [1:0] $end
$scope module test_greater $end
$var wire 2 $ a [1:0] $end
$var wire 2 % b [1:0] $end
$var wire 1 ! out $end
$upscope $end
$upscope $end
$enddefinitions $end
#0
$dumpvars
b0 %
b0 $
b0 #
b0 "
0!
$end
#1
b1 #
b1 %
#2
b10 #
b10 %
#3
b11 #
b11 %
#4
1!
b1 "
b1 $
b0 #
b0 %
#5
0!
b1 #
b1 %
#6
0!
b10 #
b10 %
#7
b11 #
b11 %
#8
1!
b10 "
b10 $
b0 #
b0 %
#9
b1 #
b1 %
#10
0!
b10 #
b10 %
#11
b11 #
b11 %
#12
1!
b11 "
b11 $
b0 #
b0 %
#13
b1 #
b1 %
#14
b10 #
b10 %
#15
0!
b11 #
b11 %
